{"cameraMode":{"drawMode":0,"name":"Shaded","section":"Shading Mode"},"sceneLighting":true,"audioPlay":false,"sceneViewState":{"m_AlwaysRefresh":false,"showFog":true,"showSkybox":true,"showFlares":true,"showImageEffects":true,"showParticleSystems":true,"showVisualEffectGraphs":true,"m_FxEnabled":true},"in2DMode":false,"pivot":{"x":18.674089431762697,"y":-5.096651077270508,"z":14.714110374450684},"rotation":{"x":-0.16725711524486543,"y":-0.3909441828727722,"z":0.07247907668352127,"w":-0.9021891355514526},"size":10.449999809265137,"orthographic":false}